RubyZhongDeYuanBiancheng/README.md
RubyZhongDeYuanBiancheng/__init__.py
RubyZhongDeYuanBiancheng/__main__.py
RubyZhongDeYuanBiancheng/file.epub
RubyZhongDeYuanBiancheng/index.html
RubyZhongDeYuanBiancheng/css/__init__.py
RubyZhongDeYuanBiancheng/css/annotations.css
RubyZhongDeYuanBiancheng/css/main.css
RubyZhongDeYuanBiancheng/css/normalize.css
RubyZhongDeYuanBiancheng/css/popup.css
RubyZhongDeYuanBiancheng/font/__init__.py
RubyZhongDeYuanBiancheng/font/fontello.eot
RubyZhongDeYuanBiancheng/font/fontello.svg
RubyZhongDeYuanBiancheng/font/fontello.ttf
RubyZhongDeYuanBiancheng/font/fontello.woff
RubyZhongDeYuanBiancheng/img/__init__.py
RubyZhongDeYuanBiancheng/img/annotator-glyph-sprite.png
RubyZhongDeYuanBiancheng/img/annotator-icon-sprite.png
RubyZhongDeYuanBiancheng/img/apple-touch-icon.png
RubyZhongDeYuanBiancheng/img/cancelfullscreen.png
RubyZhongDeYuanBiancheng/img/close.png
RubyZhongDeYuanBiancheng/img/fullscreen.png
RubyZhongDeYuanBiancheng/img/loader.gif
RubyZhongDeYuanBiancheng/img/menu-icon.png
RubyZhongDeYuanBiancheng/img/save.png
RubyZhongDeYuanBiancheng/img/saved.png
RubyZhongDeYuanBiancheng/img/settings-s.png
RubyZhongDeYuanBiancheng/img/settings.png
RubyZhongDeYuanBiancheng/img/star.png
RubyZhongDeYuanBiancheng/js/__init__.py
RubyZhongDeYuanBiancheng/js/epub.js
RubyZhongDeYuanBiancheng/js/epub.min.js
RubyZhongDeYuanBiancheng/js/epub.min.map
RubyZhongDeYuanBiancheng/js/hooks.min.js
RubyZhongDeYuanBiancheng/js/hooks.min.map
RubyZhongDeYuanBiancheng/js/reader.js
RubyZhongDeYuanBiancheng/js/reader.js.map
RubyZhongDeYuanBiancheng/js/reader.min.js
RubyZhongDeYuanBiancheng/js/reader.min.map
RubyZhongDeYuanBiancheng/js/hooks/__init__.py
RubyZhongDeYuanBiancheng/js/hooks/extensions/__init__.py
RubyZhongDeYuanBiancheng/js/hooks/extensions/highlight.js
RubyZhongDeYuanBiancheng/js/libs/__init__.py
RubyZhongDeYuanBiancheng/js/libs/jquery.min.js
RubyZhongDeYuanBiancheng/js/libs/localforage.min.js
RubyZhongDeYuanBiancheng/js/libs/screenfull.js
ruby_zhong_de_yuan_biancheng-2024.3.2.0.dist-info/METADATA
ruby_zhong_de_yuan_biancheng-2024.3.2.0.dist-info/WHEEL
ruby_zhong_de_yuan_biancheng-2024.3.2.0.dist-info/entry_points.txt
ruby_zhong_de_yuan_biancheng-2024.3.2.0.dist-info/top_level.txt
ruby_zhong_de_yuan_biancheng-2024.3.2.0.dist-info/RECORD
